<mvc:View
    controllerName="tourishui.controller.Register"
    xmlns:mvc="sap.ui.core.mvc"
    xmlns="sap.m"
    xmlns:core="sap.ui.core"
    xmlns:l="sap.ui.layout"
    displayBlock="true"
>
    <Page
        id="_IDGenPage2"
        title="Register Page"
        showNavButton="true"
        navButtonPress="onNavBack"
    >
        <content>
            <l:Grid id="_IDGenGrid5"
                defaultSpan="XL12 L12 M12 S12"
                class="sapUiMediumMargin"
            >
                <l:content>
                    <FlexBox id="_IDGenFlexBox"
                        alignItems="Center"
                        justifyContent="Center"
                        alignContent="Center"
                        wrap="Wrap"
                    >
                        <items>
                            <VBox id="_IDGenVBox55" width="40%" class="sapUiMediumMarginBegin">
                                <form:SimpleForm
                                    id="registerForm"
                                    editable="true"
                                    layout="ResponsiveGridLayout"
                                    labelSpanXL="4"
                                    labelSpanL="4"
                                    labelSpanM="4"
                                    labelSpanS="12"
                                    adjustLabelSpan="false"
                                    emptySpanXL="0"
                                    emptySpanL="0"
                                    emptySpanM="0"
                                    emptySpanS="0"
                                    columnsXL="1"
                                    columnsL="1"
                                    columnsM="1"
                                    xmlns:form="sap.ui.layout.form"
                                >
                                    <form:content>
                                        <Label id="_IDGenLabel155" text="User Name" required="true" />
                                        <Input 
                                            id="usernameInput2" 
                                            placeholder="Enter your username"
                                            liveChange="onUsernameLiveChange"
                                        />
                                        
                                        <Label id="_IDGenLabel158" text="Password" required="true" />
                                        <VBox id="_IDGenVBox56" >
                                        <Input
                                            id="passwordInput2"
                                            type="Password"
                                            placeholder="Enter your password"
                                            liveChange="onPasswordLiveChange"
                                            valueLiveUpdate="true"
                                        />
                                        <VBox id="passwordRequirements">
                                            <!-- js -->
                                        </VBox>
                                        </VBox>
                                        
                                        <Label id="_IDGenLabel159" text="Full name" required="true" />
                                        <Input 
                                            id="fullNameInput" 
                                            placeholder="Enter your full name"
                                            liveChange="onFullNameLiveChange"
                                        />
                                        
                                        <Label id="_IDGenLabel160" text="Email" required="true" />
                                        <Input 
                                            id="emailInput11" 
                                            placeholder="Enter your email"
                                            liveChange="onEmailLiveChange"
                                        />
                                        
                                        <Label id="_IDGenLabel161" text="Phone number" />
                                        <Input 
                                            id="phoneInput11" 
                                            placeholder="Enter your phone number"
                                            liveChange="onPhoneLiveChange"
                                        />
                                    </form:content>
                                </form:SimpleForm>
                                
                                <Button
                                    id="_IDGenButton1"
                                    text="Register"
                                    press="onRegisterPress"
                                    type="Emphasized"
                                    width="100%"
                                    class="sapUiSmallMarginnTop" 
                                />
                            </VBox>

                            <VBox id="_IDGenVBox57"  width="40%" class="sapUiMediumMarginBegin" alignItems="Center">
                                <Image id="_IDGenImage" 
                                    src="https://www.neovasolutions.com/wp-content/uploads/2021/05/Travel-management-system-min.png" 
                                    width="100%"
                                    height="auto"
                                    class="sapUiMediumMarginBottom" />
                                <Text id="_IDGenText172" text="Register to join our" class="sapMTitleStyleH2" textAlign="Center"/>
                                <Text id="_IDGenText173" text="Tourish Management System!" class="sapUiMediumMarginBottom sapMTitleStyleH2" textAlign="Center"/>
                            </VBox>
                            
                            
                        </items>
                    </FlexBox>
                </l:content>
            </l:Grid>
        </content>
    </Page>
</mvc:View>